{".class": "MypyFile", "_fullname": "02. Operate", "is_partial_stub_package": false, "is_stub": false, "names": {".class": "SymbolTable", "__doc__": {".class": "SymbolTableNode", "kind": "Gdef", "node": {".class": "Var", "flags": ["is_ready"], "fullname": "02. Operate.__doc__", "name": "__doc__", "type": "builtins.str"}}, "__file__": {".class": "SymbolTableNode", "kind": "Gdef", "node": {".class": "Var", "flags": ["is_ready"], "fullname": "02. Operate.__file__", "name": "__file__", "type": "builtins.str"}}, "__name__": {".class": "SymbolTableNode", "kind": "Gdef", "node": {".class": "Var", "flags": ["is_ready"], "fullname": "02. Operate.__name__", "name": "__name__", "type": "builtins.str"}}, "__package__": {".class": "SymbolTableNode", "kind": "Gdef", "node": {".class": "Var", "flags": ["is_ready"], "fullname": "02. Operate.__package__", "name": "__package__", "type": "builtins.str"}}, "multiply_nums": {".class": "SymbolTableNode", "kind": "Gdef", "node": {".class": "FuncDef", "arg_kinds": [0], "arg_names": ["nums"], "flags": [], "fullname": "02. Operate.multiply_nums", "name": "multiply_nums", "type": null}}, "operate": {".class": "SymbolTableNode", "kind": "Gdef", "node": {".class": "FuncDef", "arg_kinds": [0, 2], "arg_names": ["operator", "nums"], "flags": [], "fullname": "02. Operate.operate", "name": "operate", "type": null}}, "sum_nums": {".class": "SymbolTableNode", "kind": "Gdef", "node": {".class": "FuncDef", "arg_kinds": [0], "arg_names": ["nums"], "flags": [], "fullname": "02. Operate.sum_nums", "name": "sum_nums", "type": null}}}, "path": "05-Functions/Lab/02. Operate.py"}